netpeakPsel/__init__.py
netpeakPsel/content_parser.py
netpeakPsel/sitewide.py
netpeakPsel-0.1.5.dist-info/METADATA
netpeakPsel-0.1.5.dist-info/WHEEL
netpeakPsel-0.1.5.dist-info/top_level.txt
netpeakPsel-0.1.5.dist-info/RECORD
