Metadata-Version: 2.1
Name: netpeakPsel
Version: 0.1.5
Summary: A tool for parsing external links from specific sections of a website (header, footer, nav, aside).
Home-page: https://github.com/VsevolodKrasovskyi/netpeakPsel
Author: Masik
Author-email: v.krasovskyi@netpeak.net
License: MIT
Classifier: Development Status :: 4 - Beta
Classifier: Programming Language :: Python :: 3
Classifier: License :: OSI Approved :: MIT License
Classifier: Operating System :: OS Independent
Requires-Python: >=3.6
Requires-Dist: requests
Requires-Dist: beautifulsoup4
Requires-Dist: lxml
Requires-Dist: tqdm
Requires-Dist: colorama
